augment.py
simple_augment-1.0.dist-info/METADATA
simple_augment-1.0.dist-info/WHEEL
simple_augment-1.0.dist-info/top_level.txt
simple_augment-1.0.dist-info/RECORD
