Metadata-Version: 2.1
Name: simple-augment
Version: 1.0
Summary: A collection of small but useful Python tools.
Home-page: https://github.com/zhafen/augment
Author: Zach Hafen
Author-email: zachary.h.hafen@gmail.com
License: UNKNOWN
Platform: UNKNOWN
Classifier: Programming Language :: Python :: 3
Classifier: License :: OSI Approved :: MIT License
Classifier: Operating System :: OS Independent
